prettyip.py
test_prettyip.py
prettyip-1.1.4.dist-info/top_level.txt
prettyip-1.1.4.dist-info/METADATA
prettyip-1.1.4.dist-info/DESCRIPTION.rst
prettyip-1.1.4.dist-info/metadata.json
prettyip-1.1.4.dist-info/WHEEL
prettyip-1.1.4.dist-info/RECORD
