Metadata-Version: 2.0
Name: prettyip
Version: 1.1.4
Summary: Pretty-print IPy's IPSets 
Home-page: https://github.com/djmitche/prettyip
Author: Dustin J. Mitchell
Author-email: dustin@mozilla.com
License: MPLv2
Keywords: ipy ip pretty-print
Platform: UNKNOWN
Classifier: Development Status :: 4 - Beta
Classifier: Intended Audience :: Developers
Classifier: Topic :: System :: Networking
Classifier: Topic :: Internet
Classifier: License :: OSI Approved :: Mozilla Public License 2.0 (MPL 2.0)
Classifier: Programming Language :: Python :: 2
Classifier: Programming Language :: Python :: 2.7
Classifier: Programming Language :: Python :: 3
Classifier: Programming Language :: Python :: 3.4
Requires-Dist: IPy
Provides-Extra: test
Requires-Dist: nose; extra == 'test'
Requires-Dist: mock; extra == 'test'
